falakpy/__init__.py
falakpy/lunar.py
falakpy/prayertime.py
falakpy/qibla.py
falakpy-0.1.5.dist-info/licenses/LICENSE
falakpy-0.1.5.dist-info/METADATA
falakpy-0.1.5.dist-info/WHEEL
falakpy-0.1.5.dist-info/top_level.txt
falakpy-0.1.5.dist-info/RECORD
