Metadata-Version: 2.4
Name: falakpy
Version: 0.1.5
Summary: A Python toolkit for Islamic Astronomy (Ilm al-Falak): Qibla, Prayer Times, and Lunar Observation.
Author-email: "Dr. Muhamad Syazwan Faid" <syazwaned90@gmail.com>
License: MIT License
Project-URL: Homepage, https://github.com/msyazwanfaid/falakpy
Project-URL: Documentation, https://pypi.org/project/falakpy
Project-URL: Issues, https://github.com/msyazwanfaid/falakpy/issues
Keywords: Islamic Astronomy,Falak,Qibla,Prayer Times,Lunar Observation,Hilal,Hijri Calendar
Classifier: Development Status :: 5 - Production/Stable
Classifier: Intended Audience :: Science/Research
Classifier: Programming Language :: Python :: 3
Classifier: License :: OSI Approved :: MIT License
Classifier: Topic :: Scientific/Engineering :: Astronomy
Classifier: Topic :: Religion
Classifier: Typing :: Typed
Requires-Python: >=3.9
License-File: LICENSE
Requires-Dist: numpy
Requires-Dist: skyfield
Requires-Dist: scipy
Requires-Dist: matplotlib
Requires-Dist: tabulate
Dynamic: license-file
